ddmail_openpgp_encryptor/__init__.py
ddmail_openpgp_encryptor/__main__.py
ddmail_openpgp_encryptor/ddmail_handler.py
ddmail_openpgp_encryptor-0.0.2.dist-info/METADATA
ddmail_openpgp_encryptor-0.0.2.dist-info/WHEEL
ddmail_openpgp_encryptor-0.0.2.dist-info/entry_points.txt
ddmail_openpgp_encryptor-0.0.2.dist-info/licenses/LICENSE
ddmail_openpgp_encryptor-0.0.2.dist-info/RECORD
