Metadata-Version: 2.4
Name: ddmail_openpgp_encryptor
Version: 0.0.2
Summary: Program to encrypt incoming emails with OpenPGP for the DDMail project.
Project-URL: Homepage, https://github.com/drzobin/ddmail_openpgp_encryptor
Project-URL: Issues, https://github.com/drzobin/ddmail_openpgp_encryptor/issues
Author-email: Robin Larsson <me@drz.se>
License-Expression: AGPL-3.0
License-File: LICENSE
Classifier: Operating System :: POSIX :: Linux
Classifier: Programming Language :: Python :: 3
Requires-Python: >=3.8
Requires-Dist: aiosmtpd
Requires-Dist: ddmail-validators
Requires-Dist: mysqlclient
Requires-Dist: python-gnupg
Requires-Dist: sqlalchemy
Requires-Dist: toml
Provides-Extra: dev
Requires-Dist: aiosmtpd; extra == 'dev'
Requires-Dist: ddmail-validators; extra == 'dev'
Requires-Dist: flake8; extra == 'dev'
Requires-Dist: hatchling; extra == 'dev'
Requires-Dist: mysqlclient; extra == 'dev'
Requires-Dist: pytest; extra == 'dev'
Requires-Dist: pytest-cov; extra == 'dev'
Requires-Dist: python-gnupg; extra == 'dev'
Requires-Dist: sqlalchemy; extra == 'dev'
Requires-Dist: toml; extra == 'dev'
Requires-Dist: twine; extra == 'dev'
Provides-Extra: test
Requires-Dist: aiosmtpd; extra == 'test'
Requires-Dist: ddmail-validators; extra == 'test'
Requires-Dist: flake8; extra == 'test'
Requires-Dist: mysqlclient; extra == 'test'
Requires-Dist: pytest; extra == 'test'
Requires-Dist: pytest-cov; extra == 'test'
Requires-Dist: python-gnupg; extra == 'test'
Requires-Dist: sqlalchemy; extra == 'test'
Requires-Dist: toml; extra == 'test'
